sexup/__init__.py
sexup-0.0.1.dist-info/METADATA
sexup-0.0.1.dist-info/WHEEL
sexup-0.0.1.dist-info/licenses/LICENSE.txt
sexup-0.0.1.dist-info/RECORD
